[{"inputs":[{"internalType":"address","name":"_dremHub","type":"address"},{"internalType":"address","name":"_assetRegistry","type":"address"},{"internalType":"address","name":"_feeController","type":"address"}],"stateMutability":"nonpayable","type":"constructor"},{"inputs":[],"name":"InsufficientFunds","type":"error"},{"inputs":[],"name":"InvalidStepPosition","type":"error"},{"inputs":[],"name":"NotHubOwner","type":"error"},{"inputs":[],"name":"StepDeprecated","type":"error"},{"inputs":[],"name":"StepDisabled","type":"error"},{"inputs":[],"name":"StepLegacied","type":"error"},{"inputs":[],"name":"TransferFailed","type":"error"},{"inputs":[],"name":"ZeroAddress","type":"error"},{"inputs":[],"name":"ASSET_REGISTRY","outputs":[{"internalType":"contract IAssetRegistry","name":"","type":"address"}],"stateMutability":"view","type":"function"},{"inputs":[],"name":"DREM_HUB","outputs":[{"internalType":"contract DremHub","name":"","type":"address"}],"stateMutability":"view","type":"function"},{"inputs":[],"name":"PRICE_AGGREGATOR","outputs":[{"internalType":"contract IPriceAggregator","name":"","type":"address"}],"stateMutability":"view","type":"function"},{"inputs":[],"name":"feeController","outputs":[{"internalType":"contract IFeeController","name":"","type":"address"}],"stateMutability":"view","type":"function"},{"inputs":[{"internalType":"uint256","name":"_stepNodeKey","type":"uint256"},{"internalType":"bytes","name":"","type":"bytes"}],"name":"init","outputs":[],"stateMutability":"nonpayable","type":"function"},{"inputs":[{"internalType":"address","name":"_feeController","type":"address"}],"name":"setFeeController","outputs":[],"stateMutability":"nonpayable","type":"function"},{"inputs":[{"internalType":"address","name":"_caller","type":"address"},{"internalType":"uint256","name":"","type":"uint256"},{"internalType":"uint256","name":"_amountIn","type":"uint256"},{"internalType":"bytes","name":"","type":"bytes"}],"name":"unwind","outputs":[{"internalType":"uint256","name":"","type":"uint256"}],"stateMutability":"nonpayable","type":"function"},{"inputs":[{"internalType":"uint256","name":"","type":"uint256"},{"internalType":"address","name":"_denominationAsset","type":"address"}],"name":"value","outputs":[{"internalType":"uint256","name":"","type":"uint256"}],"stateMutability":"view","type":"function"},{"inputs":[{"internalType":"address","name":"_caller","type":"address"},{"internalType":"uint256","name":"","type":"uint256"},{"internalType":"uint256","name":"_amountIn","type":"uint256"},{"internalType":"bytes","name":"","type":"bytes"}],"name":"wind","outputs":[{"internalType":"uint256","name":"","type":"uint256"}],"stateMutability":"nonpayable","type":"function"}]